bot_common/__init__.py
bot_common/constants.py
bot_common/evaluation.py
bot_common/models/__init__.py
bot_common/models/attention.py
bot_common/models/decoder_rnn.py
bot_common/models/encoder_rnn.py
bot_common/text_processing/__init__.py
bot_common/text_processing/utils.py
bot_common/text_processing/voc.py
chatbot_common_aiqingyuyan-0.0.3.dist-info/LICENSE
chatbot_common_aiqingyuyan-0.0.3.dist-info/METADATA
chatbot_common_aiqingyuyan-0.0.3.dist-info/WHEEL
chatbot_common_aiqingyuyan-0.0.3.dist-info/top_level.txt
chatbot_common_aiqingyuyan-0.0.3.dist-info/RECORD
