Metadata-Version: 2.1
Name: chatbot-common-aiqingyuyan
Version: 0.0.3
Summary: common package for chatbot
Home-page: UNKNOWN
Author: Unknown
License: UNKNOWN
Platform: UNKNOWN
Classifier: Programming Language :: Python :: 3
Classifier: License :: OSI Approved :: MIT License
Classifier: Operating System :: OS Independent
Requires-Python: >=3.6
